CustomtkinterCodeViewer/CTkCodeViewer.py
CustomtkinterCodeViewer/__init__.py
libname/CTkCodeViewer.py
libname/__init__.py
CustomtkinterCodeViewer-0.0.3.dist-info/METADATA
CustomtkinterCodeViewer-0.0.3.dist-info/WHEEL
CustomtkinterCodeViewer-0.0.3.dist-info/top_level.txt
CustomtkinterCodeViewer-0.0.3.dist-info/RECORD
