Metadata-Version: 2.1
Name: CustomtkinterCodeViewer
Version: 0.0.3
Summary: Display syntax highlighted code in customtkinter
Author: Rigved Maanas
Author-email: <rigvedmaanas@gmail.com>
Keywords: python,customtkinter,code view,code viewer,CTkCodeViewer,tkinter
Classifier: Intended Audience :: Developers
Classifier: Programming Language :: Python :: 3
Classifier: Operating System :: Unix
Classifier: Operating System :: MacOS :: MacOS X
Classifier: Operating System :: Microsoft :: Windows
